{
  "users": [
    {
      "name": "Dr. Woodrow Abbott",
      "id": 8
    },
    {
      "name": "Bernice Barrows",
      "id": 10
    },
    {
      "name": "Inez Harber",
      "id": 12
    },
    {
      "name": "Karen Powlowski",
      "id": 13
    }
  ],
  "albums": [
    {
      "userId": 8,
      "title": "Fantastic Concrete Fish",
      "id": 13
    },
    {
      "userId": 8,
      "title": "Handmade Concrete Cheese",
      "id": 14
    },
    {
      "userId": 8,
      "title": "Gorgeous Granite Chicken",
      "id": 15
    }
  ],
  "photos": []
}